cli/__init__.py
cli/an_es.py
cli/auto_test.py
cli/main.py
cmd_request/CMD_REQUEST.py
cmd_request/__init__.py
config/__init__.py
config/config.py
es_util/ESTOOL.py
es_util/__init__.py
log/LOG.py
log/__init__.py
report/__init__.py
algo_cmd-1.1.3.dist-info/METADATA
algo_cmd-1.1.3.dist-info/WHEEL
algo_cmd-1.1.3.dist-info/entry_points.txt
algo_cmd-1.1.3.dist-info/top_level.txt
algo_cmd-1.1.3.dist-info/RECORD
