Metadata-Version: 2.1
Name: algo-cmd
Version: 1.1.3
Requires-Dist: setuptools
Requires-Dist: requests
